pytldr
