Metadata-Version: 1.1
Name: PyTLDR
Version: 0.1.4
Summary: A module to perform automatic article summarization.
Home-page: https://github.com/jaijuneja/PyTLDR
Author: Jai Juneja
Author-email: jai.juneja@gmail.com
License: BSD
Keywords: summarizer,summarization,natural language processing,nlp,machine learning,data mining,latent semantic analysis,lsa
Platform: UNKNOWN
Classifier: Development Status :: 3 - Alpha
Classifier: Topic :: Scientific/Engineering :: Artificial Intelligence
Classifier: Topic :: Scientific/Engineering :: Information Analysis
Classifier: Topic :: Text Processing :: Filters
Classifier: Topic :: Text Processing :: Linguistic
Classifier: Intended Audience :: Developers
Classifier: License :: OSI Approved :: BSD License
Classifier: Operating System :: OS Independent
Classifier: Programming Language :: Python
